unittest_seven_helper/__init__.py
unittest_seven_helper/__main__.py
unittest_seven_helper/abstract_data_provider.py
unittest_seven_helper/abstract_testcase.py
unittest_seven_helper/attrs_manager.py
unittest_seven_helper/attrs_marker.py
unittest_seven_helper/depends.py
unittest_seven_helper/errors.py
unittest_seven_helper/excel_file_reader.py
unittest_seven_helper/global_config.py
unittest_seven_helper/main.py
unittest_seven_helper/report_builder.py
unittest_seven_helper/result_formatter.py
unittest_seven_helper/seven_data_provider.py
unittest_seven_helper/seven_loader.py
unittest_seven_helper/seven_result.py
unittest_seven_helper/seven_runner.py
unittest_seven_helper/test_wrapper.py
unittest_seven_helper/utils.py
unittest_seven_helper/report/__init__.py
unittest_seven_helper/report/htmltemplate.py
unittest_seven_helper/report/html/__init__.py
unittest_seven_helper/report/html/elements.py
unittest_seven_helper/report/html/tags.py
unittest_seven_helper/report/resources/bitbug_favicon.ico
unittest_seven_helper/report/resources/jquery-1.11.0.min.js
unittest_seven_helper/report/resources/main.js
unittest_seven_helper/report/resources/seventester.ico
unittest_seven_helper/report/resources/style.css
unittest_seven_helper/report/widgets/__init__.py
unittest_seven_helper/report/widgets/piechart.py
unittest_seven_helper/report/widgets/tables.py
unittest_seven_helper/samples/CalculationTest.xlsx
unittest_seven_helper/samples/__init__.py
unittest_seven_helper/samples/calculation_test.py
unittest_seven_helper/samples/dependency_test.py
unittest_seven_helper-2.1.0.dist-info/LICENSE
unittest_seven_helper-2.1.0.dist-info/METADATA
unittest_seven_helper-2.1.0.dist-info/WHEEL
unittest_seven_helper-2.1.0.dist-info/top_level.txt
unittest_seven_helper-2.1.0.dist-info/RECORD
